{"id": "7718a9cf-7e77-406d-b660-7d7a70388295", "timestamp": "2025-04-22T20:47:40.751163", "videoName": "2d0707e9-b0de-49d2-bb7b-f94f18dc9670.mp4", "roadName": "Kala Pathar", "roadLocation": "Indiarapuram", "roadSegments": [{"id": "segment-0", "startCoordinates": {"latitude": 28.6139, "longitude": 77.209}, "endCoordinates": {"latitude": 28.6144, "longitude": 77.209}, "condition": "good", "confidence": 0.9640187038012494}, {"id": "segment-1", "startCoordinates": {"latitude": 28.6144, "longitude": 77.209}, "endCoordinates": {"latitude": 28.614899958469525, "longitude": 77.20899355571956}, "condition": "fair", "confidence": 0.9008854102736534}, {"id": "segment-2", "startCoordinates": {"latitude": 28.614899958469525, "longitude": 77.20899355571956}, "endCoordinates": {"latitude": 28.61539917042929, "longitude": 77.20902161671079}, "condition": "good", "confidence": 0.8330356080992012}, {"id": "segment-3", "startCoordinates": {"latitude": 28.61539917042929, "longitude": 77.20902161671079}, "endCoordinates": {"latitude": 28.61589897152729, "longitude": 77.20903571857005}, "condition": "good", "confidence": 0.9616754873160522}, {"id": "segment-4", "startCoordinates": {"latitude": 28.61589897152729, "longitude": 77.20903571857005}, "endCoordinates": {"latitude": 28.61639595721569, "longitude": 77.20909053850734}, "condition": "good", "confidence": 0.9931865001491607}, {"id": "segment-5", "startCoordinates": {"latitude": 28.61639595721569, "longitude": 77.20909053850734}, "endCoordinates": {"latitude": 28.616894359202345, "longitude": 77.20913048171327}, "condition": "good", "confidence": 0.7885239690299256}, {"id": "segment-6", "startCoordinates": {"latitude": 28.616894359202345, "longitude": 77.20913048171327}, "endCoordinates": {"latitude": 28.617394351313504, "longitude": 77.20913329041028}, "condition": "fair", "confidence": 0.73175369646081}, {"id": "segment-7", "startCoordinates": {"latitude": 28.617394351313504, "longitude": 77.20913329041028}, "endCoordinates": {"latitude": 28.61789383903758, "longitude": 77.20911066269507}, "condition": "bad", "confidence": 0.7040543844292304}, {"id": "segment-8", "startCoordinates": {"latitude": 28.61789383903758, "longitude": 77.20911066269507}, "endCoordinates": {"latitude": 28.61839119693068, "longitude": 77.20905932921505}, "condition": "good", "confidence": 0.807214040360829}, {"id": "segment-9", "startCoordinates": {"latitude": 28.61839119693068, "longitude": 77.20905932921505}, "endCoordinates": {"latitude": 28.618887411292828, "longitude": 77.20899791824861}, "condition": "good", "confidence": 0.9437939217052441}, {"id": "segment-10", "startCoordinates": {"latitude": 28.618887411292828, "longitude": 77.20899791824861}, "endCoordinates": {"latitude": 28.619386891247235, "longitude": 77.20897511967085}, "condition": "bad", "confidence": 0.7372805599029598}, {"id": "segment-11", "startCoordinates": {"latitude": 28.619386891247235, "longitude": 77.20897511967085}, "endCoordinates": {"latitude": 28.619883657095667, "longitude": 77.20891834210634}, "condition": "good", "confidence": 0.9035253865557784}, {"id": "segment-12", "startCoordinates": {"latitude": 28.619883657095667, "longitude": 77.20891834210634}, "endCoordinates": {"latitude": 28.620381959929606, "longitude": 77.20887718040464}, "condition": "bad", "confidence": 0.7799248476438371}, {"id": "segment-13", "startCoordinates": {"latitude": 28.620381959929606, "longitude": 77.20887718040464}, "endCoordinates": {"latitude": 28.620880071059474, "longitude": 77.20883376033666}, "condition": "fair", "confidence": 0.8469657214707613}, {"id": "segment-14", "startCoordinates": {"latitude": 28.620880071059474, "longitude": 77.20883376033666}, "endCoordinates": {"latitude": 28.621378795710985, "longitude": 77.20879807109493}, "condition": "good", "confidence": 0.7707182266214347}, {"id": "segment-15", "startCoordinates": {"latitude": 28.621378795710985, "longitude": 77.20879807109493}, "endCoordinates": {"latitude": 28.62187513833451, "longitude": 77.20873770554122}, "condition": "good", "confidence": 0.9380808045100824}, {"id": "segment-16", "startCoordinates": {"latitude": 28.62187513833451, "longitude": 77.20873770554122}, "endCoordinates": {"latitude": 28.622367686935313, "longitude": 77.20865170626304}, "condition": "good", "confidence": 0.8425326503880993}, {"id": "segment-17", "startCoordinates": {"latitude": 28.622367686935313, "longitude": 77.20865170626304}, "endCoordinates": {"latitude": 28.622861119732825, "longitude": 77.20857093452084}, "condition": "bad", "confidence": 0.7448362638812173}, {"id": "segment-18", "startCoordinates": {"latitude": 28.622861119732825, "longitude": 77.20857093452084}, "endCoordinates": {"latitude": 28.623350201088403, "longitude": 77.20846701422624}, "condition": "fair", "confidence": 0.8523641386874372}], "detectedFrames": []}